figma_query/__init__.py
figma_query/__main__.py
figma_query/cli.py
figma_query/bin/.gitkeep
figma_query/bin/figma-query-darwin-amd64
figma_query/bin/figma-query-darwin-arm64
figma_query/bin/figma-query-linux-amd64
figma_query/bin/figma-query-linux-arm64
figma_query-0.1.0.dist-info/METADATA
figma_query-0.1.0.dist-info/WHEEL
figma_query-0.1.0.dist-info/entry_points.txt
figma_query-0.1.0.dist-info/RECORD
