Metadata-Version: 2.4
Name: figma-query
Version: 0.1.0
Summary: Token-efficient Figma MCP server with image export, query DSL, and design token support
Project-URL: Homepage, https://github.com/standardbeagle/figma-query
Project-URL: Repository, https://github.com/standardbeagle/figma-query
Project-URL: Issues, https://github.com/standardbeagle/figma-query/issues
Author: StandardBeagle
License-Expression: MIT
Keywords: css,design-system,design-tokens,figma,mcp,model-context-protocol
Classifier: Development Status :: 4 - Beta
Classifier: Environment :: Console
Classifier: Intended Audience :: Developers
Classifier: License :: OSI Approved :: MIT License
Classifier: Operating System :: MacOS
Classifier: Operating System :: Microsoft :: Windows
Classifier: Operating System :: POSIX :: Linux
Classifier: Programming Language :: Python :: 3
Classifier: Programming Language :: Python :: 3.9
Classifier: Programming Language :: Python :: 3.10
Classifier: Programming Language :: Python :: 3.11
Classifier: Programming Language :: Python :: 3.12
Classifier: Topic :: Software Development :: Libraries
Requires-Python: >=3.9
